.gitignore
LICENSE
README.md
requirements_strict
setup.py
doc/Makefile
doc/conf.py
doc/hybridizing_extra.rst
doc/index.rst
doc/installation.rst
doc/loading.rst
doc/quickstart.rst
doc/sorting.rst
doc/img/auto_hybrid.png
doc/img/display_template.png
doc/img/display_template.svg
doc/img/inspect_fit.png
doc/img/inspect_fit.svg
doc/img/relocate_train.png
doc/img/relocate_train.svg
examples/spikeinterface_conversion_example.py
examples/spikeinterface_validation_example.py
examples/validation_example.py
hybridizer/__init__.py
hybridizer/hybrid.py
hybridizer/io.py
hybridizer/probes.py
hybridizer/shybrid.py
hybridizer/spikes.py
hybridizer/threads.py
hybridizer/validation.py
hybridizer/ui/__init__.py
hybridizer/ui/design.py
hybridizer/ui/import_template.py
hybridizer/ui/insert_template.py
hybridizer/ui/select_auto.py
img/screenshot.png
shybrid.egg-info/PKG-INFO
shybrid.egg-info/SOURCES.txt
shybrid.egg-info/dependency_links.txt
shybrid.egg-info/entry_points.txt
shybrid.egg-info/requires.txt
shybrid.egg-info/top_level.txt