Metadata-Version: 2.1
Name: shybrid
Version: 0.4.3
Summary: A graphical tool for generating hybrid ground-truth spiking data for evaluating spike sorting performance
Home-page: https://github.com/jwouters91/shybrid
Author: Jasper Wouters
Author-email: jasper.wouters@esat.kuleuven.be
License: UNKNOWN
Platform: UNKNOWN
Classifier: Programming Language :: Python :: 3
Classifier: License :: OSI Approved :: GNU General Public License v3 (GPLv3)
Classifier: Operating System :: OS Independent
Requires-Python: >=3.6
